{
  "nombre" : "Wesley Koolhof",
  "mano" : "R",
  "nacionalidad" : "NED",
  "edad" : 25.9301848049,
  "ganar1Saque" : 0.8148148059844971,
  "ganar2Saque" : 0.4761904776096344,
  "primerSaque" : 0.529411792755127,
  "segundoSaque" : 0.4117647111415863,
  "ganarPuntoSacando" : 0.6274510016609787,
  "ganarPuntoRestando" : 0.22448980268010388,
  "probAce" : 0.019607843831181526,
  "clay" : {
    "nombre" : "Clay",
    "probVictoria" : 0.0,
    "probGanarPrimerSaque" : 0.0,
    "probGanarSegundoSaque" : 0.0,
    "probPrimerSaque" : 0.0,
    "probSegundoSaque" : 0.0,
    "probGanarPuntoSacando" : 0.0,
    "probGanarPuntoRestando" : 0.0,
    "probAce" : 0.0
  },
  "grass" : {
    "nombre" : "Grass",
    "probVictoria" : 0.0,
    "probGanarPrimerSaque" : 0.0,
    "probGanarSegundoSaque" : 0.0,
    "probPrimerSaque" : 0.0,
    "probSegundoSaque" : 0.0,
    "probGanarPuntoSacando" : 0.0,
    "probGanarPuntoRestando" : 0.0,
    "probAce" : 0.0
  },
  "hard" : {
    "nombre" : "Hard",
    "probVictoria" : 0.0,
    "probGanarPrimerSaque" : 0.8148148059844971,
    "probGanarSegundoSaque" : 0.4761904776096344,
    "probPrimerSaque" : 0.529411792755127,
    "probSegundoSaque" : 0.4117647111415863,
    "probGanarPuntoSacando" : 0.6274510016609787,
    "probGanarPuntoRestando" : 0.22448980268010388,
    "probAce" : 0.0
  },
  "other" : {
    "nombre" : "Other",
    "probVictoria" : 0.0,
    "probGanarPrimerSaque" : 0.0,
    "probGanarSegundoSaque" : 0.0,
    "probPrimerSaque" : 0.0,
    "probSegundoSaque" : 0.0,
    "probGanarPuntoSacando" : 0.0,
    "probGanarPuntoRestando" : 0.0,
    "probAce" : 0.0
  },
  "partidos" : [ {
    "torneo" : "Le Gosier CH",
    "fecha" : "20150331",
    "superficie" : "Hard",
    "resultado" : "6-3 6-3",
    "contrincante" : "Jan Hernych",
    "ganador" : false,
    "winnerAces" : 4,
    "winnerPrimerSaqueDentro" : 33,
    "winnerPrimerSaqueGanado" : 28,
    "winnerSegundoSaqueGanado" : 10,
    "winnerDobleFalta" : 0,
    "winnerServingPoints" : 49,
    "winnerServingGames" : 9,
    "loserAces" : 1,
    "loserPrimerSaqueDentro" : 27,
    "loserPrimerSaqueGanado" : 22,
    "loserSegundoSaqueGanado" : 10,
    "loserDobleFalta" : 3,
    "loserServingPoints" : 51,
    "loserServingGames" : 9
  }, {
    "torneo" : "Bogota Q",
    "fecha" : "20150720",
    "superficie" : "Hard",
    "resultado" : "6-3 7-6(5)",
    "contrincante" : "Chris Guccione",
    "ganador" : false,
    "winnerAces" : 0,
    "winnerPrimerSaqueDentro" : 0,
    "winnerPrimerSaqueGanado" : 0,
    "winnerSegundoSaqueGanado" : 0,
    "winnerDobleFalta" : 0,
    "winnerServingPoints" : 0,
    "winnerServingGames" : 0,
    "loserAces" : 0,
    "loserPrimerSaqueDentro" : 0,
    "loserPrimerSaqueGanado" : 0,
    "loserSegundoSaqueGanado" : 0,
    "loserDobleFalta" : 0,
    "loserServingPoints" : 0,
    "loserServingGames" : 0
  } ]
}