{
  "nombre" : "Christian Voinea",
  "mano" : "U",
  "nacionalidad" : "ROU",
  "edad" : 0.0,
  "ganar1Saque" : 0.5555555820465088,
  "ganar2Saque" : 0.6428571343421936,
  "primerSaque" : 0.41860464215278625,
  "segundoSaque" : 0.3255814015865326,
  "ganarPuntoSacando" : 0.44186047243759496,
  "ganarPuntoRestando" : 0.125,
  "probAce" : 0.0,
  "clay" : {
    "nombre" : "Clay",
    "probVictoria" : 0.0,
    "probGanarPrimerSaque" : 0.0,
    "probGanarSegundoSaque" : 0.0,
    "probPrimerSaque" : 0.0,
    "probSegundoSaque" : 0.0,
    "probGanarPuntoSacando" : 0.0,
    "probGanarPuntoRestando" : 0.0,
    "probAce" : 0.0
  },
  "grass" : {
    "nombre" : "Grass",
    "probVictoria" : 0.0,
    "probGanarPrimerSaque" : 0.0,
    "probGanarSegundoSaque" : 0.0,
    "probPrimerSaque" : 0.0,
    "probSegundoSaque" : 0.0,
    "probGanarPuntoSacando" : 0.0,
    "probGanarPuntoRestando" : 0.0,
    "probAce" : 0.0
  },
  "hard" : {
    "nombre" : "Hard",
    "probVictoria" : 0.0,
    "probGanarPrimerSaque" : 0.5555555820465088,
    "probGanarSegundoSaque" : 0.6428571343421936,
    "probPrimerSaque" : 0.41860464215278625,
    "probSegundoSaque" : 0.3255814015865326,
    "probGanarPuntoSacando" : 0.44186047243759496,
    "probGanarPuntoRestando" : 0.125,
    "probAce" : 0.0
  },
  "other" : {
    "nombre" : "Other",
    "probVictoria" : 0.0,
    "probGanarPrimerSaque" : 0.0,
    "probGanarSegundoSaque" : 0.0,
    "probPrimerSaque" : 0.0,
    "probSegundoSaque" : 0.0,
    "probGanarPuntoSacando" : 0.0,
    "probGanarPuntoRestando" : 0.0,
    "probAce" : 0.0
  },
  "partidos" : [ {
    "torneo" : "Segovia CH",
    "fecha" : "20110801",
    "superficie" : "Hard",
    "resultado" : "6-2 6-1",
    "contrincante" : "Evgeny Donskoy",
    "ganador" : false,
    "winnerAces" : 0,
    "winnerPrimerSaqueDentro" : 11,
    "winnerPrimerSaqueGanado" : 11,
    "winnerSegundoSaqueGanado" : 17,
    "winnerDobleFalta" : 1,
    "winnerServingPoints" : 32,
    "winnerServingGames" : 7,
    "loserAces" : 0,
    "loserPrimerSaqueDentro" : 18,
    "loserPrimerSaqueGanado" : 10,
    "loserSegundoSaqueGanado" : 9,
    "loserDobleFalta" : 11,
    "loserServingPoints" : 43,
    "loserServingGames" : 8
  } ]
}