{
  "nombre" : "Chuhan Wang",
  "mano" : "U",
  "nacionalidad" : "CHN",
  "edad" : 19.5482546201,
  "ganar1Saque" : 0.6380545496940613,
  "ganar2Saque" : 0.36006192366282147,
  "primerSaque" : 0.5704157054424286,
  "segundoSaque" : 0.3632964293162028,
  "ganarPuntoSacando" : 0.4947655472739153,
  "ganarPuntoRestando" : 0.22499997837521993,
  "probAce" : 0.019108280539512634,
  "clay" : {
    "nombre" : "Clay",
    "probVictoria" : 0.0,
    "probGanarPrimerSaque" : 0.0,
    "probGanarSegundoSaque" : 0.0,
    "probPrimerSaque" : 0.0,
    "probSegundoSaque" : 0.0,
    "probGanarPuntoSacando" : 0.0,
    "probGanarPuntoRestando" : 0.0,
    "probAce" : 0.0
  },
  "grass" : {
    "nombre" : "Grass",
    "probVictoria" : 0.0,
    "probGanarPrimerSaque" : 0.0,
    "probGanarSegundoSaque" : 0.0,
    "probPrimerSaque" : 0.0,
    "probSegundoSaque" : 0.0,
    "probGanarPuntoSacando" : 0.0,
    "probGanarPuntoRestando" : 0.0,
    "probAce" : 0.0
  },
  "hard" : {
    "nombre" : "Hard",
    "probVictoria" : 0.0,
    "probGanarPrimerSaque" : 0.6380545496940613,
    "probGanarSegundoSaque" : 0.36006192366282147,
    "probPrimerSaque" : 0.5704157054424286,
    "probSegundoSaque" : 0.3632964293162028,
    "probGanarPuntoSacando" : 0.4947655472739153,
    "probGanarPuntoRestando" : 0.22499997837521993,
    "probAce" : 0.0
  },
  "other" : {
    "nombre" : "Other",
    "probVictoria" : 0.0,
    "probGanarPrimerSaque" : 0.0,
    "probGanarSegundoSaque" : 0.0,
    "probPrimerSaque" : 0.0,
    "probSegundoSaque" : 0.0,
    "probGanarPuntoSacando" : 0.0,
    "probGanarPuntoRestando" : 0.0,
    "probAce" : 0.0
  },
  "partidos" : [ {
    "torneo" : "Ningbo CH",
    "fecha" : "20110912",
    "superficie" : "Hard",
    "resultado" : "6-3 6-1",
    "contrincante" : "Dominik Meffert",
    "ganador" : false,
    "winnerAces" : 3,
    "winnerPrimerSaqueDentro" : 22,
    "winnerPrimerSaqueGanado" : 19,
    "winnerSegundoSaqueGanado" : 13,
    "winnerDobleFalta" : 1,
    "winnerServingPoints" : 40,
    "winnerServingGames" : 8,
    "loserAces" : 0,
    "loserPrimerSaqueDentro" : 26,
    "loserPrimerSaqueGanado" : 17,
    "loserSegundoSaqueGanado" : 7,
    "loserDobleFalta" : 3,
    "loserServingPoints" : 48,
    "loserServingGames" : 8
  }, {
    "torneo" : "Wuhai CH",
    "fecha" : "20110725",
    "superficie" : "Hard",
    "resultado" : "6-2 6-4",
    "contrincante" : "Tsung Hua Yang",
    "ganador" : false,
    "winnerAces" : 5,
    "winnerPrimerSaqueDentro" : 26,
    "winnerPrimerSaqueGanado" : 22,
    "winnerSegundoSaqueGanado" : 14,
    "winnerDobleFalta" : 1,
    "winnerServingPoints" : 45,
    "winnerServingGames" : 9,
    "loserAces" : 2,
    "loserPrimerSaqueDentro" : 45,
    "loserPrimerSaqueGanado" : 31,
    "loserSegundoSaqueGanado" : 6,
    "loserDobleFalta" : 0,
    "loserServingPoints" : 65,
    "loserServingGames" : 9
  }, {
    "torneo" : "Shanghai Masters Q",
    "fecha" : "20111009",
    "superficie" : "Hard",
    "resultado" : "6-1 6-1",
    "contrincante" : "Simone Bolelli",
    "ganador" : false,
    "winnerAces" : 3,
    "winnerPrimerSaqueDentro" : 23,
    "winnerPrimerSaqueGanado" : 16,
    "winnerSegundoSaqueGanado" : 13,
    "winnerDobleFalta" : 0,
    "winnerServingPoints" : 40,
    "winnerServingGames" : 7,
    "loserAces" : 1,
    "loserPrimerSaqueDentro" : 21,
    "loserPrimerSaqueGanado" : 12,
    "loserSegundoSaqueGanado" : 7,
    "loserDobleFalta" : 6,
    "loserServingPoints" : 44,
    "loserServingGames" : 7
  } ]
}