{
  "nombre" : "John Patrick Smith",
  "mano" : "L",
  "nacionalidad" : "AUS",
  "edad" : 21.7713894593,
  "ganar1Saque" : 0.6907756924629211,
  "ganar2Saque" : 0.5716578563054403,
  "primerSaque" : 0.6294049719969431,
  "segundoSaque" : 0.343179648121198,
  "ganarPuntoSacando" : 0.6309589973434133,
  "ganarPuntoRestando" : 0.35614351068956146,
  "probAce" : 0.048245612531900406,
  "clay" : {
    "nombre" : "Clay",
    "probVictoria" : 0.0,
    "probGanarPrimerSaque" : 0.0,
    "probGanarSegundoSaque" : 0.0,
    "probPrimerSaque" : 0.0,
    "probSegundoSaque" : 0.0,
    "probGanarPuntoSacando" : 0.0,
    "probGanarPuntoRestando" : 0.0,
    "probAce" : 0.0
  },
  "grass" : {
    "nombre" : "Grass",
    "probVictoria" : 0.0,
    "probGanarPrimerSaque" : 0.0,
    "probGanarSegundoSaque" : 0.0,
    "probPrimerSaque" : 0.0,
    "probSegundoSaque" : 0.0,
    "probGanarPuntoSacando" : 0.0,
    "probGanarPuntoRestando" : 0.0,
    "probAce" : 0.0
  },
  "hard" : {
    "nombre" : "Hard",
    "probVictoria" : 0.5,
    "probGanarPrimerSaque" : 0.6907756924629211,
    "probGanarSegundoSaque" : 0.5716578563054403,
    "probPrimerSaque" : 0.6294049719969431,
    "probSegundoSaque" : 0.343179648121198,
    "probGanarPuntoSacando" : 0.6309589973434133,
    "probGanarPuntoRestando" : 0.35614351068956146,
    "probAce" : 0.0
  },
  "other" : {
    "nombre" : "Other",
    "probVictoria" : 0.0,
    "probGanarPrimerSaque" : 0.0,
    "probGanarSegundoSaque" : 0.0,
    "probPrimerSaque" : 0.0,
    "probSegundoSaque" : 0.0,
    "probGanarPuntoSacando" : 0.0,
    "probGanarPuntoRestando" : 0.0,
    "probAce" : 0.0
  },
  "partidos" : [ {
    "torneo" : "Tulsa CH",
    "fecha" : "20110912",
    "superficie" : "Hard",
    "resultado" : "6-1 6-7(3) 6-4",
    "contrincante" : "Adam El Mihdawy",
    "ganador" : true,
    "winnerAces" : 2,
    "winnerPrimerSaqueDentro" : 63,
    "winnerPrimerSaqueGanado" : 45,
    "winnerSegundoSaqueGanado" : 18,
    "winnerDobleFalta" : 2,
    "winnerServingPoints" : 99,
    "winnerServingGames" : 15,
    "loserAces" : 3,
    "loserPrimerSaqueDentro" : 47,
    "loserPrimerSaqueGanado" : 34,
    "loserSegundoSaqueGanado" : 13,
    "loserDobleFalta" : 6,
    "loserServingPoints" : 85,
    "loserServingGames" : 14
  }, {
    "torneo" : "Tulsa CH",
    "fecha" : "20110912",
    "superficie" : "Hard",
    "resultado" : "7-5 6-2",
    "contrincante" : "Tim Smyczek",
    "ganador" : false,
    "winnerAces" : 1,
    "winnerPrimerSaqueDentro" : 36,
    "winnerPrimerSaqueGanado" : 22,
    "winnerSegundoSaqueGanado" : 15,
    "winnerDobleFalta" : 3,
    "winnerServingPoints" : 55,
    "winnerServingGames" : 10,
    "loserAces" : 1,
    "loserPrimerSaqueDentro" : 33,
    "loserPrimerSaqueGanado" : 19,
    "loserSegundoSaqueGanado" : 9,
    "loserDobleFalta" : 3,
    "loserServingPoints" : 58,
    "loserServingGames" : 10
  }, {
    "torneo" : "Knoxville CH",
    "fecha" : "20111107",
    "superficie" : "Hard",
    "resultado" : "7-5 5-7 6-3",
    "contrincante" : "Amer Delic",
    "ganador" : false,
    "winnerAces" : 9,
    "winnerPrimerSaqueDentro" : 72,
    "winnerPrimerSaqueGanado" : 53,
    "winnerSegundoSaqueGanado" : 19,
    "winnerDobleFalta" : 4,
    "winnerServingPoints" : 107,
    "winnerServingGames" : 17,
    "loserAces" : 4,
    "loserPrimerSaqueDentro" : 75,
    "loserPrimerSaqueGanado" : 49,
    "loserSegundoSaqueGanado" : 20,
    "loserDobleFalta" : 0,
    "loserServingPoints" : 109,
    "loserServingGames" : 16
  }, {
    "torneo" : "Champaign CH",
    "fecha" : "20111114",
    "superficie" : "Hard",
    "resultado" : "6-4 7-6(5)",
    "contrincante" : "Dennis Nevolo",
    "ganador" : true,
    "winnerAces" : 7,
    "winnerPrimerSaqueDentro" : 36,
    "winnerPrimerSaqueGanado" : 29,
    "winnerSegundoSaqueGanado" : 16,
    "winnerDobleFalta" : 1,
    "winnerServingPoints" : 58,
    "winnerServingGames" : 11,
    "loserAces" : 0,
    "loserPrimerSaqueDentro" : 41,
    "loserPrimerSaqueGanado" : 29,
    "loserSegundoSaqueGanado" : 13,
    "loserDobleFalta" : 1,
    "loserServingPoints" : 63,
    "loserServingGames" : 11
  }, {
    "torneo" : "Champaign CH",
    "fecha" : "20111114",
    "superficie" : "Hard",
    "resultado" : "6-4 6-4",
    "contrincante" : "Pierre Ludovic Duclos",
    "ganador" : true,
    "winnerAces" : 2,
    "winnerPrimerSaqueDentro" : 33,
    "winnerPrimerSaqueGanado" : 26,
    "winnerSegundoSaqueGanado" : 15,
    "winnerDobleFalta" : 2,
    "winnerServingPoints" : 55,
    "winnerServingGames" : 10,
    "loserAces" : 8,
    "loserPrimerSaqueDentro" : 32,
    "loserPrimerSaqueGanado" : 27,
    "loserSegundoSaqueGanado" : 14,
    "loserDobleFalta" : 6,
    "loserServingPoints" : 69,
    "loserServingGames" : 10
  }, {
    "torneo" : "Champaign CH",
    "fecha" : "20111114",
    "superficie" : "Hard",
    "resultado" : "6-2 6-4",
    "contrincante" : "Peter Polansky",
    "ganador" : false,
    "winnerAces" : 4,
    "winnerPrimerSaqueDentro" : 36,
    "winnerPrimerSaqueGanado" : 28,
    "winnerSegundoSaqueGanado" : 10,
    "winnerDobleFalta" : 1,
    "winnerServingPoints" : 54,
    "winnerServingGames" : 9,
    "loserAces" : 6,
    "loserPrimerSaqueDentro" : 51,
    "loserPrimerSaqueGanado" : 31,
    "loserSegundoSaqueGanado" : 9,
    "loserDobleFalta" : 3,
    "loserServingPoints" : 77,
    "loserServingGames" : 9
  } ]
}