{
  "nombre" : "Simon Stadler",
  "mano" : "L",
  "nacionalidad" : "GER",
  "edad" : 22.9349760438,
  "ganar1Saque" : 0.6779661178588867,
  "ganar2Saque" : 0.3571428656578064,
  "primerSaque" : 0.6781609058380127,
  "segundoSaque" : 0.3218390941619873,
  "ganarPuntoSacando" : 0.5747126529843882,
  "ganarPuntoRestando" : 0.35000004074942836,
  "probAce" : 0.02298850566148758,
  "clay" : {
    "nombre" : "Clay",
    "probVictoria" : 0.6000000238418579,
    "probGanarPrimerSaque" : 0.0,
    "probGanarSegundoSaque" : 0.0,
    "probPrimerSaque" : 0.0,
    "probSegundoSaque" : 0.0,
    "probGanarPuntoSacando" : 0.0,
    "probGanarPuntoRestando" : 0.0,
    "probAce" : 0.0
  },
  "grass" : {
    "nombre" : "Grass",
    "probVictoria" : 0.0,
    "probGanarPrimerSaque" : 0.6779661178588867,
    "probGanarSegundoSaque" : 0.3571428656578064,
    "probPrimerSaque" : 0.6781609058380127,
    "probSegundoSaque" : 0.3218390941619873,
    "probGanarPuntoSacando" : 0.5747126529843882,
    "probGanarPuntoRestando" : 0.35000004074942836,
    "probAce" : 0.0
  },
  "hard" : {
    "nombre" : "Hard",
    "probVictoria" : 0.550000011920929,
    "probGanarPrimerSaque" : 0.0,
    "probGanarSegundoSaque" : 0.0,
    "probPrimerSaque" : 0.0,
    "probSegundoSaque" : 0.0,
    "probGanarPuntoSacando" : 0.0,
    "probGanarPuntoRestando" : 0.0,
    "probAce" : 0.0
  },
  "other" : {
    "nombre" : "Other",
    "probVictoria" : 0.0,
    "probGanarPrimerSaque" : 0.0,
    "probGanarSegundoSaque" : 0.0,
    "probPrimerSaque" : 0.0,
    "probSegundoSaque" : 0.0,
    "probGanarPuntoSacando" : 0.0,
    "probGanarPuntoRestando" : 0.0,
    "probAce" : 0.0
  },
  "partidos" : [ {
    "torneo" : "Wimbledon",
    "fecha" : "20060626",
    "superficie" : "Grass",
    "resultado" : "6-1 6-4 6-4",
    "contrincante" : "David Ferrer",
    "ganador" : false,
    "winnerAces" : 1,
    "winnerPrimerSaqueDentro" : 71,
    "winnerPrimerSaqueGanado" : 52,
    "winnerSegundoSaqueGanado" : 13,
    "winnerDobleFalta" : 3,
    "winnerServingPoints" : 100,
    "winnerServingGames" : 14,
    "loserAces" : 2,
    "loserPrimerSaqueDentro" : 59,
    "loserPrimerSaqueGanado" : 40,
    "loserSegundoSaqueGanado" : 10,
    "loserDobleFalta" : 0,
    "loserServingPoints" : 87,
    "loserServingGames" : 13
  }, {
    "torneo" : "Rimouski CH",
    "fecha" : "20061030",
    "superficie" : "Hard",
    "resultado" : "6-3 4-6 6-4",
    "contrincante" : "Frederik Nielsen",
    "ganador" : true,
    "winnerAces" : 0,
    "winnerPrimerSaqueDentro" : 0,
    "winnerPrimerSaqueGanado" : 0,
    "winnerSegundoSaqueGanado" : 0,
    "winnerDobleFalta" : 0,
    "winnerServingPoints" : 0,
    "winnerServingGames" : 0,
    "loserAces" : 0,
    "loserPrimerSaqueDentro" : 0,
    "loserPrimerSaqueGanado" : 0,
    "loserSegundoSaqueGanado" : 0,
    "loserDobleFalta" : 0,
    "loserServingPoints" : 0,
    "loserServingGames" : 0
  }, {
    "torneo" : "Rimouski CH",
    "fecha" : "20061030",
    "superficie" : "Hard",
    "resultado" : "7-6(3) 7-5",
    "contrincante" : "Gary Lugassy",
    "ganador" : false,
    "winnerAces" : 0,
    "winnerPrimerSaqueDentro" : 0,
    "winnerPrimerSaqueGanado" : 0,
    "winnerSegundoSaqueGanado" : 0,
    "winnerDobleFalta" : 0,
    "winnerServingPoints" : 0,
    "winnerServingGames" : 0,
    "loserAces" : 0,
    "loserPrimerSaqueDentro" : 0,
    "loserPrimerSaqueGanado" : 0,
    "loserSegundoSaqueGanado" : 0,
    "loserDobleFalta" : 0,
    "loserServingPoints" : 0,
    "loserServingGames" : 0
  }, {
    "torneo" : "Vancouver CH",
    "fecha" : "20060731",
    "superficie" : "Hard",
    "resultado" : "6-3 7-6(2)",
    "contrincante" : "Eric Taino",
    "ganador" : false,
    "winnerAces" : 0,
    "winnerPrimerSaqueDentro" : 0,
    "winnerPrimerSaqueGanado" : 0,
    "winnerSegundoSaqueGanado" : 0,
    "winnerDobleFalta" : 0,
    "winnerServingPoints" : 0,
    "winnerServingGames" : 0,
    "loserAces" : 0,
    "loserPrimerSaqueDentro" : 0,
    "loserPrimerSaqueGanado" : 0,
    "loserSegundoSaqueGanado" : 0,
    "loserDobleFalta" : 0,
    "loserServingPoints" : 0,
    "loserServingGames" : 0
  }, {
    "torneo" : "Banja Luka CH",
    "fecha" : "20060918",
    "superficie" : "Clay",
    "resultado" : "6-4 7-6(6)",
    "contrincante" : "Ivan Dodig",
    "ganador" : true,
    "winnerAces" : 0,
    "winnerPrimerSaqueDentro" : 0,
    "winnerPrimerSaqueGanado" : 0,
    "winnerSegundoSaqueGanado" : 0,
    "winnerDobleFalta" : 0,
    "winnerServingPoints" : 0,
    "winnerServingGames" : 0,
    "loserAces" : 0,
    "loserPrimerSaqueDentro" : 0,
    "loserPrimerSaqueGanado" : 0,
    "loserSegundoSaqueGanado" : 0,
    "loserDobleFalta" : 0,
    "loserServingPoints" : 0,
    "loserServingGames" : 0
  }, {
    "torneo" : "Banja Luka CH",
    "fecha" : "20060918",
    "superficie" : "Clay",
    "resultado" : "6-1 6-7(4) 6-4",
    "contrincante" : "Federico Luzzi",
    "ganador" : false,
    "winnerAces" : 0,
    "winnerPrimerSaqueDentro" : 0,
    "winnerPrimerSaqueGanado" : 0,
    "winnerSegundoSaqueGanado" : 0,
    "winnerDobleFalta" : 0,
    "winnerServingPoints" : 0,
    "winnerServingGames" : 0,
    "loserAces" : 0,
    "loserPrimerSaqueDentro" : 0,
    "loserPrimerSaqueGanado" : 0,
    "loserSegundoSaqueGanado" : 0,
    "loserDobleFalta" : 0,
    "loserServingPoints" : 0,
    "loserServingGames" : 0
  }, {
    "torneo" : "Donetsk CH",
    "fecha" : "20060904",
    "superficie" : "Clay",
    "resultado" : "6-1 6-0",
    "contrincante" : "Dmitry Frumkin",
    "ganador" : true,
    "winnerAces" : 0,
    "winnerPrimerSaqueDentro" : 0,
    "winnerPrimerSaqueGanado" : 0,
    "winnerSegundoSaqueGanado" : 0,
    "winnerDobleFalta" : 0,
    "winnerServingPoints" : 0,
    "winnerServingGames" : 0,
    "loserAces" : 0,
    "loserPrimerSaqueDentro" : 0,
    "loserPrimerSaqueGanado" : 0,
    "loserSegundoSaqueGanado" : 0,
    "loserDobleFalta" : 0,
    "loserServingPoints" : 0,
    "loserServingGames" : 0
  }, {
    "torneo" : "Donetsk CH",
    "fecha" : "20060904",
    "superficie" : "Clay",
    "resultado" : "7-5 2-0 RET",
    "contrincante" : "Philipp Petzschner",
    "ganador" : true,
    "winnerAces" : 0,
    "winnerPrimerSaqueDentro" : 0,
    "winnerPrimerSaqueGanado" : 0,
    "winnerSegundoSaqueGanado" : 0,
    "winnerDobleFalta" : 0,
    "winnerServingPoints" : 0,
    "winnerServingGames" : 0,
    "loserAces" : 0,
    "loserPrimerSaqueDentro" : 0,
    "loserPrimerSaqueGanado" : 0,
    "loserSegundoSaqueGanado" : 0,
    "loserDobleFalta" : 0,
    "loserServingPoints" : 0,
    "loserServingGames" : 0
  }, {
    "torneo" : "Donetsk CH",
    "fecha" : "20060904",
    "superficie" : "Clay",
    "resultado" : "6-3 7-5",
    "contrincante" : "Ilija Bozoljac",
    "ganador" : false,
    "winnerAces" : 0,
    "winnerPrimerSaqueDentro" : 0,
    "winnerPrimerSaqueGanado" : 0,
    "winnerSegundoSaqueGanado" : 0,
    "winnerDobleFalta" : 0,
    "winnerServingPoints" : 0,
    "winnerServingGames" : 0,
    "loserAces" : 0,
    "loserPrimerSaqueDentro" : 0,
    "loserPrimerSaqueGanado" : 0,
    "loserSegundoSaqueGanado" : 0,
    "loserDobleFalta" : 0,
    "loserServingPoints" : 0,
    "loserServingGames" : 0
  }, {
    "torneo" : "Mons CH",
    "fecha" : "20061002",
    "superficie" : "Hard",
    "resultado" : "6-2 6-1",
    "contrincante" : "Roko Karanusic",
    "ganador" : true,
    "winnerAces" : 0,
    "winnerPrimerSaqueDentro" : 0,
    "winnerPrimerSaqueGanado" : 0,
    "winnerSegundoSaqueGanado" : 0,
    "winnerDobleFalta" : 0,
    "winnerServingPoints" : 0,
    "winnerServingGames" : 0,
    "loserAces" : 0,
    "loserPrimerSaqueDentro" : 0,
    "loserPrimerSaqueGanado" : 0,
    "loserSegundoSaqueGanado" : 0,
    "loserDobleFalta" : 0,
    "loserServingPoints" : 0,
    "loserServingGames" : 0
  }, {
    "torneo" : "Mons CH",
    "fecha" : "20061002",
    "superficie" : "Hard",
    "resultado" : "6-2 6-1",
    "contrincante" : "Olivier Rochus",
    "ganador" : false,
    "winnerAces" : 0,
    "winnerPrimerSaqueDentro" : 0,
    "winnerPrimerSaqueGanado" : 0,
    "winnerSegundoSaqueGanado" : 0,
    "winnerDobleFalta" : 0,
    "winnerServingPoints" : 0,
    "winnerServingGames" : 0,
    "loserAces" : 0,
    "loserPrimerSaqueDentro" : 0,
    "loserPrimerSaqueGanado" : 0,
    "loserSegundoSaqueGanado" : 0,
    "loserDobleFalta" : 0,
    "loserServingPoints" : 0,
    "loserServingGames" : 0
  }, {
    "torneo" : "Cardiff CH",
    "fecha" : "20060417",
    "superficie" : "Hard",
    "resultado" : "6-2 1-6 6-4",
    "contrincante" : "Igor Kunitsyn",
    "ganador" : true,
    "winnerAces" : 0,
    "winnerPrimerSaqueDentro" : 0,
    "winnerPrimerSaqueGanado" : 0,
    "winnerSegundoSaqueGanado" : 0,
    "winnerDobleFalta" : 0,
    "winnerServingPoints" : 0,
    "winnerServingGames" : 0,
    "loserAces" : 0,
    "loserPrimerSaqueDentro" : 0,
    "loserPrimerSaqueGanado" : 0,
    "loserSegundoSaqueGanado" : 0,
    "loserDobleFalta" : 0,
    "loserServingPoints" : 0,
    "loserServingGames" : 0
  }, {
    "torneo" : "Cardiff CH",
    "fecha" : "20060417",
    "superficie" : "Hard",
    "resultado" : "6-3 7-5",
    "contrincante" : "Uros Vico",
    "ganador" : false,
    "winnerAces" : 0,
    "winnerPrimerSaqueDentro" : 0,
    "winnerPrimerSaqueGanado" : 0,
    "winnerSegundoSaqueGanado" : 0,
    "winnerDobleFalta" : 0,
    "winnerServingPoints" : 0,
    "winnerServingGames" : 0,
    "loserAces" : 0,
    "loserPrimerSaqueDentro" : 0,
    "loserPrimerSaqueGanado" : 0,
    "loserSegundoSaqueGanado" : 0,
    "loserDobleFalta" : 0,
    "loserServingPoints" : 0,
    "loserServingGames" : 0
  }, {
    "torneo" : "Lanzarote CH",
    "fecha" : "20060424",
    "superficie" : "Hard",
    "resultado" : "6-4 6-7(5) 6-3",
    "contrincante" : "Gregory Carraz",
    "ganador" : true,
    "winnerAces" : 0,
    "winnerPrimerSaqueDentro" : 0,
    "winnerPrimerSaqueGanado" : 0,
    "winnerSegundoSaqueGanado" : 0,
    "winnerDobleFalta" : 0,
    "winnerServingPoints" : 0,
    "winnerServingGames" : 0,
    "loserAces" : 0,
    "loserPrimerSaqueDentro" : 0,
    "loserPrimerSaqueGanado" : 0,
    "loserSegundoSaqueGanado" : 0,
    "loserDobleFalta" : 0,
    "loserServingPoints" : 0,
    "loserServingGames" : 0
  }, {
    "torneo" : "Lanzarote CH",
    "fecha" : "20060424",
    "superficie" : "Hard",
    "resultado" : "6-3 6-3",
    "contrincante" : "Gary Lugassy",
    "ganador" : true,
    "winnerAces" : 0,
    "winnerPrimerSaqueDentro" : 0,
    "winnerPrimerSaqueGanado" : 0,
    "winnerSegundoSaqueGanado" : 0,
    "winnerDobleFalta" : 0,
    "winnerServingPoints" : 0,
    "winnerServingGames" : 0,
    "loserAces" : 0,
    "loserPrimerSaqueDentro" : 0,
    "loserPrimerSaqueGanado" : 0,
    "loserSegundoSaqueGanado" : 0,
    "loserDobleFalta" : 0,
    "loserServingPoints" : 0,
    "loserServingGames" : 0
  }, {
    "torneo" : "Lanzarote CH",
    "fecha" : "20060424",
    "superficie" : "Hard",
    "resultado" : "6-3 6-2",
    "contrincante" : "Kenneth Carlsen",
    "ganador" : true,
    "winnerAces" : 0,
    "winnerPrimerSaqueDentro" : 0,
    "winnerPrimerSaqueGanado" : 0,
    "winnerSegundoSaqueGanado" : 0,
    "winnerDobleFalta" : 0,
    "winnerServingPoints" : 0,
    "winnerServingGames" : 0,
    "loserAces" : 0,
    "loserPrimerSaqueDentro" : 0,
    "loserPrimerSaqueGanado" : 0,
    "loserSegundoSaqueGanado" : 0,
    "loserDobleFalta" : 0,
    "loserServingPoints" : 0,
    "loserServingGames" : 0
  }, {
    "torneo" : "Lanzarote CH",
    "fecha" : "20060424",
    "superficie" : "Hard",
    "resultado" : "6-3 6-4",
    "contrincante" : "Jo Wilfried Tsonga",
    "ganador" : false,
    "winnerAces" : 0,
    "winnerPrimerSaqueDentro" : 0,
    "winnerPrimerSaqueGanado" : 0,
    "winnerSegundoSaqueGanado" : 0,
    "winnerDobleFalta" : 0,
    "winnerServingPoints" : 0,
    "winnerServingGames" : 0,
    "loserAces" : 0,
    "loserPrimerSaqueDentro" : 0,
    "loserPrimerSaqueGanado" : 0,
    "loserSegundoSaqueGanado" : 0,
    "loserDobleFalta" : 0,
    "loserServingPoints" : 0,
    "loserServingGames" : 0
  }, {
    "torneo" : "Rennes CH",
    "fecha" : "20061009",
    "superficie" : "Hard",
    "resultado" : "6-7(4) 6-2 6-4",
    "contrincante" : "Lukas Dlouhy",
    "ganador" : false,
    "winnerAces" : 0,
    "winnerPrimerSaqueDentro" : 0,
    "winnerPrimerSaqueGanado" : 0,
    "winnerSegundoSaqueGanado" : 0,
    "winnerDobleFalta" : 0,
    "winnerServingPoints" : 0,
    "winnerServingGames" : 0,
    "loserAces" : 0,
    "loserPrimerSaqueDentro" : 0,
    "loserPrimerSaqueGanado" : 0,
    "loserSegundoSaqueGanado" : 0,
    "loserDobleFalta" : 0,
    "loserServingPoints" : 0,
    "loserServingGames" : 0
  }, {
    "torneo" : "Busan CH",
    "fecha" : "20060529",
    "superficie" : "Hard",
    "resultado" : "6-0 6-0",
    "contrincante" : "Yu Jr Wang",
    "ganador" : true,
    "winnerAces" : 0,
    "winnerPrimerSaqueDentro" : 0,
    "winnerPrimerSaqueGanado" : 0,
    "winnerSegundoSaqueGanado" : 0,
    "winnerDobleFalta" : 0,
    "winnerServingPoints" : 0,
    "winnerServingGames" : 0,
    "loserAces" : 0,
    "loserPrimerSaqueDentro" : 0,
    "loserPrimerSaqueGanado" : 0,
    "loserSegundoSaqueGanado" : 0,
    "loserDobleFalta" : 0,
    "loserServingPoints" : 0,
    "loserServingGames" : 0
  }, {
    "torneo" : "Busan CH",
    "fecha" : "20060529",
    "superficie" : "Hard",
    "resultado" : "7-5 7-6(3)",
    "contrincante" : "John Paul Fruttero",
    "ganador" : true,
    "winnerAces" : 0,
    "winnerPrimerSaqueDentro" : 0,
    "winnerPrimerSaqueGanado" : 0,
    "winnerSegundoSaqueGanado" : 0,
    "winnerDobleFalta" : 0,
    "winnerServingPoints" : 0,
    "winnerServingGames" : 0,
    "loserAces" : 0,
    "loserPrimerSaqueDentro" : 0,
    "loserPrimerSaqueGanado" : 0,
    "loserSegundoSaqueGanado" : 0,
    "loserDobleFalta" : 0,
    "loserServingPoints" : 0,
    "loserServingGames" : 0
  }, {
    "torneo" : "Busan CH",
    "fecha" : "20060529",
    "superficie" : "Hard",
    "resultado" : "6-1 6-1",
    "contrincante" : "Cecil Mamiit",
    "ganador" : false,
    "winnerAces" : 0,
    "winnerPrimerSaqueDentro" : 0,
    "winnerPrimerSaqueGanado" : 0,
    "winnerSegundoSaqueGanado" : 0,
    "winnerDobleFalta" : 0,
    "winnerServingPoints" : 0,
    "winnerServingGames" : 0,
    "loserAces" : 0,
    "loserPrimerSaqueDentro" : 0,
    "loserPrimerSaqueGanado" : 0,
    "loserSegundoSaqueGanado" : 0,
    "loserDobleFalta" : 0,
    "loserServingPoints" : 0,
    "loserServingGames" : 0
  }, {
    "torneo" : "Granby CH",
    "fecha" : "20060724",
    "superficie" : "Hard",
    "resultado" : "6-4 6-4",
    "contrincante" : "Gary Lugassy",
    "ganador" : true,
    "winnerAces" : 0,
    "winnerPrimerSaqueDentro" : 0,
    "winnerPrimerSaqueGanado" : 0,
    "winnerSegundoSaqueGanado" : 0,
    "winnerDobleFalta" : 0,
    "winnerServingPoints" : 0,
    "winnerServingGames" : 0,
    "loserAces" : 0,
    "loserPrimerSaqueDentro" : 0,
    "loserPrimerSaqueGanado" : 0,
    "loserSegundoSaqueGanado" : 0,
    "loserDobleFalta" : 0,
    "loserServingPoints" : 0,
    "loserServingGames" : 0
  }, {
    "torneo" : "Granby CH",
    "fecha" : "20060724",
    "superficie" : "Hard",
    "resultado" : "6-2 6-4",
    "contrincante" : "Matej Bocko",
    "ganador" : true,
    "winnerAces" : 0,
    "winnerPrimerSaqueDentro" : 0,
    "winnerPrimerSaqueGanado" : 0,
    "winnerSegundoSaqueGanado" : 0,
    "winnerDobleFalta" : 0,
    "winnerServingPoints" : 0,
    "winnerServingGames" : 0,
    "loserAces" : 0,
    "loserPrimerSaqueDentro" : 0,
    "loserPrimerSaqueGanado" : 0,
    "loserSegundoSaqueGanado" : 0,
    "loserDobleFalta" : 0,
    "loserServingPoints" : 0,
    "loserServingGames" : 0
  }, {
    "torneo" : "Granby CH",
    "fecha" : "20060724",
    "superficie" : "Hard",
    "resultado" : "6-1 6-3",
    "contrincante" : "Frank Dancevic",
    "ganador" : false,
    "winnerAces" : 0,
    "winnerPrimerSaqueDentro" : 0,
    "winnerPrimerSaqueGanado" : 0,
    "winnerSegundoSaqueGanado" : 0,
    "winnerDobleFalta" : 0,
    "winnerServingPoints" : 0,
    "winnerServingGames" : 0,
    "loserAces" : 0,
    "loserPrimerSaqueDentro" : 0,
    "loserPrimerSaqueGanado" : 0,
    "loserSegundoSaqueGanado" : 0,
    "loserDobleFalta" : 0,
    "loserServingPoints" : 0,
    "loserServingGames" : 0
  }, {
    "torneo" : "Aptos CH",
    "fecha" : "20060717",
    "superficie" : "Hard",
    "resultado" : "6-3 6-4",
    "contrincante" : "Ronald Agenor",
    "ganador" : true,
    "winnerAces" : 0,
    "winnerPrimerSaqueDentro" : 0,
    "winnerPrimerSaqueGanado" : 0,
    "winnerSegundoSaqueGanado" : 0,
    "winnerDobleFalta" : 0,
    "winnerServingPoints" : 0,
    "winnerServingGames" : 0,
    "loserAces" : 0,
    "loserPrimerSaqueDentro" : 0,
    "loserPrimerSaqueGanado" : 0,
    "loserSegundoSaqueGanado" : 0,
    "loserDobleFalta" : 0,
    "loserServingPoints" : 0,
    "loserServingGames" : 0
  }, {
    "torneo" : "Aptos CH",
    "fecha" : "20060717",
    "superficie" : "Hard",
    "resultado" : "6-4 6-4",
    "contrincante" : "Ivo Heuberger",
    "ganador" : false,
    "winnerAces" : 0,
    "winnerPrimerSaqueDentro" : 0,
    "winnerPrimerSaqueGanado" : 0,
    "winnerSegundoSaqueGanado" : 0,
    "winnerDobleFalta" : 0,
    "winnerServingPoints" : 0,
    "winnerServingGames" : 0,
    "loserAces" : 0,
    "loserPrimerSaqueDentro" : 0,
    "loserPrimerSaqueGanado" : 0,
    "loserSegundoSaqueGanado" : 0,
    "loserDobleFalta" : 0,
    "loserServingPoints" : 0,
    "loserServingGames" : 0
  } ]
}